dagster_components/__init__.py
dagster_components/dagster.py
dagster_components/dagster_dbt.py
dagster_components/dagster_sling.py
dagster_components/version.py
dagster_components-0.26.9.dist-info/LICENSE
dagster_components-0.26.9.dist-info/METADATA
dagster_components-0.26.9.dist-info/WHEEL
dagster_components-0.26.9.dist-info/entry_points.txt
dagster_components-0.26.9.dist-info/top_level.txt
dagster_components-0.26.9.dist-info/RECORD
