Metadata-Version: 2.1
Name: dagster-components
Version: 0.26.9
Home-page: https://github.com/dagster-io/dagster/tree/master/examples/experimental/dagster-components/dagster-components
Author: Dagster Labs
Author-email: hello@dagsterlabs.com
License: Apache-2.0
Classifier: Programming Language :: Python :: 3.9
Classifier: Programming Language :: Python :: 3.10
Classifier: Programming Language :: Python :: 3.11
Classifier: Programming Language :: Python :: 3.12
Classifier: License :: OSI Approved :: Apache Software License
Classifier: Operating System :: OS Independent
License-File: LICENSE
Requires-Dist: dagster ==1.10.9
Requires-Dist: typer
